pm4py/__init__.py
pm4py/analysis.py
pm4py/cli.py
pm4py/conformance.py
pm4py/connectors.py
pm4py/convert.py
pm4py/discovery.py
pm4py/filtering.py
pm4py/hof.py
pm4py/llm.py
pm4py/meta.py
pm4py/ml.py
pm4py/ocel.py
pm4py/org.py
pm4py/privacy.py
pm4py/read.py
pm4py/sim.py
pm4py/stats.py
pm4py/utils.py
pm4py/vis.py
pm4py/write.py
pm4py/algo/__init__.py
pm4py/algo/analysis/__init__.py
pm4py/algo/analysis/extended_marking_equation/__init__.py
pm4py/algo/analysis/extended_marking_equation/algorithm.py
pm4py/algo/analysis/extended_marking_equation/variants/__init__.py
pm4py/algo/analysis/extended_marking_equation/variants/classic.py
pm4py/algo/analysis/marking_equation/__init__.py
pm4py/algo/analysis/marking_equation/algorithm.py
pm4py/algo/analysis/marking_equation/variants/__init__.py
pm4py/algo/analysis/marking_equation/variants/classic.py
pm4py/algo/analysis/woflan/__init__.py
pm4py/algo/analysis/woflan/algorithm.py
pm4py/algo/analysis/woflan/graphs/__init__.py
pm4py/algo/analysis/woflan/graphs/utility.py
pm4py/algo/analysis/woflan/graphs/minimal_coverability_graph/__init__.py
pm4py/algo/analysis/woflan/graphs/minimal_coverability_graph/minimal_coverability_graph.py
pm4py/algo/analysis/woflan/graphs/reachability_graph/__init__.py
pm4py/algo/analysis/woflan/graphs/reachability_graph/reachability_graph.py
pm4py/algo/analysis/woflan/graphs/restricted_coverability_graph/__init__.py
pm4py/algo/analysis/woflan/graphs/restricted_coverability_graph/restricted_coverability_graph.py
pm4py/algo/analysis/woflan/not_well_handled_pairs/__init__.py
pm4py/algo/analysis/woflan/not_well_handled_pairs/not_well_handled_pairs.py
pm4py/algo/analysis/woflan/place_invariants/__init__.py
pm4py/algo/analysis/woflan/place_invariants/place_invariants.py
pm4py/algo/analysis/woflan/place_invariants/s_component.py
pm4py/algo/analysis/woflan/place_invariants/uniform_invariant.py
pm4py/algo/analysis/woflan/place_invariants/utility.py
pm4py/algo/analysis/workflow_net/__init__.py
pm4py-2.7.19.7.dist-info/licenses/LICENSE
pm4py-2.7.19.7.dist-info/METADATA
pm4py-2.7.19.7.dist-info/WHEEL
pm4py-2.7.19.7.dist-info/top_level.txt
pm4py-2.7.19.7.dist-info/RECORD
